Workbook

Sheet TEGAL JAYA (Groceries)
A1: DATE | B1: ITEM | C1: INV NO. | D1: QYT | E1: PRICE | F1: SUBTOTAL | G1: TOTAL | H1: =SUM(G:G) -> 2687700 | I1: =H1+'[1]TEGAL JAYA (Bar Groceries)'!$H$1 -> 5475000
A2: 46114 | B2: ROSEMARY | C2: 9230 | D2: 0.1 | E2: 140000 | F2: =E2*D2 -> 14000 | G2: =SUM(F2:F8) -> 90900
B3: PARSLEY | D3: 0.1 | E3: 85000 | F3: =E3*D3 -> 8500
B4: CORIANDER | D4: 0.1 | E4: 60000 | F4: =E4*D4 -> 6000
B5: BASIL | D5: 0.1 | E5: 60000 | F5: =E5*D5 -> 6000
B6: MINT LEAVES | D6: 0.1 | E6: 50000 | F6: =E6*D6 -> 5000
B7: LIME | D7: 0.4 | E7: 16000 | F7: =E7*D7 -> 6400
B8: IMPORTED LEMON | D8: 1 | E8: 45000 | F8: =E8*D8 -> 45000
A9: 46120 | B9: HONEY PINEAPPLE | C9: 9426 | D9: 5 | E9: 12000 | F9: =E9*D9 -> 60000 | G9: =SUM(F9:F15) -> 313000
B10: IMPORTED LEMON | D10: 2 | E10: 45000 | F10: =E10*D10 -> 90000
B11: STRAWBERRY | D11: 1 | E11: 80000 | F11: =E11*D11 -> 80000
B12: PARSLEY | D12: 0.1 | E12: 85000 | F12: =E12*D12 -> 8500
B13: CORIANDER | D13: 0.1 | E13: 85000 | F13: =E13*D13 -> 8500
B14: SPRING ONION | D14: 0.1 | E14: 60000 | F14: =E14*D14 -> 6000
B15: KINTAMANI ORANGE | D15: 2 | E15: 30000 | F15: =E15*D15 -> 60000
A16: 46122 | B16: BABY CUCUMBER | C16: 10969 | D16: 1 | E16: 65000 | F16: =E16*D16 -> 65000 | G16: =SUM(F16:F27) -> 603700
B17: JALAPENO | D17: 1 | E17: 180000 | F17: =E17*D17 -> 180000
B18: PARSLEY | D18: 0.1 | E18: 80000 | F18: =E18*D18 -> 8000
B19: CORIANDER | D19: 0.1 | E19: 65000 | F19: =E19*D19 -> 6500
B20: SPRING ONION | D20: 0.07 | E20: 60000 | F20: =E20*D20 -> 4200
B21: BBQ SAUCE | D21: 2 | E21: 50000 | F21: =E21*D21 -> 100000
B22: HONEY | D22: 2 | E22: 48000 | F22: =E22*D22 -> 96000
B23: STRAWBERRY | D23: 0.5 | E23: 80000 | F23: =E23*D23 -> 40000
B24: IMPORTED LEMON | D24: 1 | E24: 45000 | F24: =E24*D24 -> 45000
B25: SUNKIST | D25: 1 | E25: 45000 | F25: =E25*D25 -> 45000
B26: BASIL | D26: 0.15 | E26: 60000 | F26: =E26*D26 -> 9000
B27: MINT LEAVES | D27: 0.1 | E27: 50000 | F27: =E27*D27 -> 5000
A28: 46125 | B28: PARSLEY | C28: 11475 | D28: 0.1 | E28: 80000 | F28: =E28*D28 -> 8000 | G28: =SUM(F28:F32) -> 118750
B29: LEEK | D29: 0.25 | E29: 35000 | F29: =E29*D29 -> 8750
B30: BASIL | D30: 0.1 | E30: 70000 | F30: =E30*D30 -> 7000
B31: MINT LEAVES | D31: 0.1 | E31: 50000 | F31: =E31*D31 -> 5000
B32: IMPORTED LEMON | D32: 2 | E32: 45000 | F32: =E32*D32 -> 90000
A33: 46126 | B33: BLACK OLIVE | C33: 11290 | D33: 2 | E33: 70000 | F33: =E33*D33 -> 140000 | G33: =SUM(F33:F38) -> 421000
B34: CORIANDER | D34: 0.1 | E34: 80000 | F34: =E34*D34 -> 8000
B35: PARSLEY | D35: 0.1 | E35: 80000 | F35: =E35*D35 -> 8000
B36: ASPARAGUS | D36: 1 | E36: 140000 | F36: =E36*D36 -> 140000
B37: SUNKIST | D37: 1 | E37: 35000 | F37: =E37*D37 -> 35000
B38: IMPORTED LEMON | D38: 2 | E38: 45000 | F38: =E38*D38 -> 90000
A39: 46127 | B39: IMPORTED LEMON | C39: N/A | D39: 1 | E39: 45000 | F39: =E39*D39 -> 45000 | G39: =SUM(F39:F47) -> 520350
B40: PARSLEY | D40: 0.07 | E40: 85000 | F40: =E40*D40 -> 5950
B41: CORIANDER | D41: 0.1 | E41: 80000 | F41: =E41*D41 -> 8000
B42: SPRING ONION | D42: 0.08 | E42: 55000 | F42: =E42*D42 -> 4400
B43: LEEK | D43: 0.2 | E43: 35000 | F43: =E43*D43 -> 7000
B44: BBQ SAUCE | D44: 3 | E44: 50000 | F44: =E44*D44 -> 150000
B45: BABY CUCUMBER | D45: 1 | E45: 75000 | F45: =E45*D45 -> 75000
B46: CASHEW NUT | D46: 1 | E46: 185000 | F46: =E46*D46 -> 185000
B47: STRAWBERRY | D47: 0.5 | E47: 80000 | F47: =E47*D47 -> 40000
A48: 46128 | B48: PARSLEY | C48: 9096 | D48: 0.1 | E48: 80000 | F48: =E48*D48 -> 8000 | G48: =SUM(F48:F52) -> 74000
B49: CORIANDER | D49: 0.1 | E49: 80000 | F49: =E49*D49 -> 8000
B50: CELERY | D50: 0.1 | E50: 50000 | F50: =E50*D50 -> 5000
B51: IMPORTED LEMON | D51: 1 | E51: 45000 | F51: =E51*D51 -> 45000
B52: BASIL | D52: 0.1 | E52: 80000 | F52: =E52*D52 -> 8000
A53: 46129 | B53: IMPORTED LEMON | C53: 4074 | D53: 1 | E53: 45000 | F53: =E53*D53 -> 45000 | G53: =SUM(F53:F63) -> 546000
B54: RED PEPPER | D54: 0.5 | E54: 100000 | F54: =E54*D54 -> 50000
B55: YELLOW PEPPER | D55: 0.6 | E55: 120000 | F55: =E55*D55 -> 72000
B56: GREEN PEPPER | D56: 0.6 | E56: 80000 | F56: =E56*D56 -> 48000
B57: PARSLEY | D57: 0.1 | E57: 85000 | F57: =E57*D57 -> 8500
B58: CORIANDER | D58: 0.15 | E58: 90000 | F58: =E58*D58 -> 13500
B59: EGGS | D59: 90 | E59: 1900 | F59: =E59*D59 -> 171000
B60: BBQ SAUCE | D60: 2 | E60: 60000 | F60: =E60*D60 -> 120000
B61: LIME | D61: 0.25 | E61: 16000 | F61: =E61*D61 -> 4000
B62: BASIL | D62: 0.1 | E62: 90000 | F62: =E62*D62 -> 9000
B63: MINT LEAVES | D63: 0.1 | E63: 50000 | F63: =E63*D63 -> 5000
A132: GRAND TOTAL | E132: =SUM(G2:G131) -> 2687700

Sheet BUK BUNGA (Groceries)
A1: DATE | B1: ITEM | C1: QYT | D1: PRICE | E1: SUBTOTAL | F1: TOTAL | G1: =SUM(F:F) -> 25635000
A2: 46113 | B2: SOUR CREAM | C2: 2 | D2: 170000 | E2: =D2*C2 -> 340000 | F2: =SUM(E2:E20) -> 2150000
B3: ROSEMARY | C3: 0.07 | D3: 150000 | E3: 11000
B4: DILL | C4: 0.1 | D4: 100000 | E4: =D4*C4 -> 10000
B5: PARSLEY | C5: 0.1 | D5: 90000 | E5: =D5*C5 -> 9000
B6: MILAC WHIPPING CREAM | C6: 2 | D6: 100000 | E6: =D6*C6 -> 200000
B7: COCONUT CREAM (KARA) | C7: 1 | D7: 220000 | E7: =D7*C7 -> 220000
B8: CASHEW NUT | C8: 1 | D8: 160000 | E8: =D8*C8 -> 160000
B9: BBQ SAUCE | C9: 5 | D9: 40000 | E9: =D9*C9 -> 200000
B10: SOY SAUCE | C10: 1 | D10: 20000 | E10: =D10*C10 -> 20000
B11: VANILA ESSENCE BUTTERFLY | C11: 3 | D11: 15000 | E11: =D11*C11 -> 45000
B12: IMPORTED LEMON | C12: 1 | D12: 70000 | E12: =D12*C12 -> 70000
B13: DOUBLE ZERO | C13: 1 | D13: 220000 | E13: =D13*C13 -> 220000
B14: SEMOLINA | C14: 1 | D14: 55000 | E14: =D14*C14 -> 55000
B15: LADY FINGER | C15: 2 | D15: 55000 | E15: =D15*C15 -> 110000
... B20: PLASTIC KILOAN | C20: 1 | D20: 20000 | E20: =D20*C20 -> 20000
A21: 46115 | B21: SOUR CREAM | C21: 1 | D21: 170000 | E21: =D21*C21 -> 170000 | F21: =SUM(E21:E37) -> 2196000
B22: PARSLEY | C22: 0.1 | D22: 100000 | E22: =D22*C22 -> 10000
B23: CORIANDER | C23: 0.07 | D23: 80000 | E23: 6000
B24: SPRING ONION | C24: 0.07 | D24: 80000 | E24: 6000
B25: CELERY | C25: 0.07 | D25: 60000 | E25: 4000
B26: BACON (1KG) | C26: 2 | D26: 170000 | E26: =D26*C26 -> 340000
B27: OREGANO | C27: 3 | D27: 30000 | E27: =D27*C27 -> 90000
B28: CHILLI FLAKES | C28: 2 | D28: 30000 | E28: =D28*C28 -> 60000
B29: SESAME DRESSING | C29: 2 | D29: 120000 | E29: =D29*C29 -> 240000
B30: IMPORTED LEMON | C30: 2 | D30: 70000 | E30: =D30*C30 -> 140000
B31: SUNKIST | C31: 1 | D31: 50000 | E31: =D31*C31 -> 50000
B32: DOUBLE ZERO | C32: 1 | D32: 220000 | E32: =D32*C32 -> 220000
B33: MIX BERRY | C33: 1 | D33: 130000 | E33: =D33*C33 -> 130000
B34: YELLOW CHEDDAR SLICE | C34: 10 | D34: 15000 | E34: =D34*C34 -> 150000
B35: FETA CHEESE | C35: 2 | D35: 90000 | E35: =D35*C35 -> 180000
B36: MILAC WHIPPING CREAM | C36: 3 | D36: 100000 | E36: =D36*C36 -> 300000
B37: ACID CITROEN (GADJAH) | C37: 20 | D37: 5000 | E37: =D37*C37 -> 100000
A38: 46116 | B38: YEAST | C38: 1 | D38: 60000 | E38: =D38*C38 -> 60000 | F38: =SUM(E38:E40) -> 330000
B39: CREAM CHEESE | C39: 1 | D39: 170000 | E39: =D39*C39 -> 170000
B40: MUSHROOM BUTTON | C40: 2 | D40: 50000 | E40: =D40*C40 -> 100000
A41: 46117 | B41: MILAC WHIPPING CREAM | C41: 8 | D41: 100000 | E41: =D41*C41 -> 800000 | F41: =SUM(E41:E55) -> 2516000
B42: BANGKOK SAUCE | C42: 2 | D42: 20000 | E42: =D42*C42 -> 40000
B43: BAKED BEAN | C43: 2 | D43: 30000 | E43: =D43*C43 -> 60000
B44: WHOLE WHEAT FLOUR (500GR) | C44: 2 | D44: 70000 | E44: =D44*C44 -> 140000
B45: KEWPIE MAYONNAISE | C45: 2 | D45: 100000 | E45: =D45*C45 -> 200000
B46: SOUR CREAM | C46: 2 | D46: 170000 | E46: =D46*C46 -> 340000
B47: CELERY | C47: 0.1 | D47: 60000 | E47: =D47*C47 -> 6000
B48: PARSLEY | C48: 0.15 | D48: 90000 | E48: 14000
B49: LEEK | C49: 0.1 | D49: 25000 | E49: 3000
B50: BABY KYURI | C50: 1 | D50: 70000 | E50: =D50*C50 -> 70000
B51: CHICK PEAS (400 GR) | C51: 3 | D51: 35000 | E51: =D51*C51 -> 105000
B52: BASIL | C52: 0.1 | D52: 80000 | E52: =D52*C52 -> 8000
B53: BRIE | C53: 1 | D53: 120000 | E53: =D53*C53 -> 120000
B54: FRENCH FRIES (1KG) | C54: 6 | D54: 45000 | E54: =D54*C54 -> 270000
B55: BACON (1KG) | C55: 2 | D55: 170000 | E55: =D55*C55 -> 340000
A56: 46118 | B56: MILAC WHIPPING CREAM | C56: 3 | D56: 100000 | E56: =D56*C56 -> 300000 | F56: =SUM(E56:E76) -> 1803000
B57: CREAM CHEESE | C57: 1 | D57: 170000 | E57: =D57*C57 -> 170000
B58: MAESTRO MAYONNAISE | C58: 2 | D58: 40000 | E58: =D58*C58 -> 80000
B59: KEWPIE MAYONNAISE | C59: 2 | D59: 100000 | E59: =D59*C59 -> 200000
B60: CELERY | C60: 0.1 | D60: 60000 | E60: =D60*C60 -> 6000
B61: DILL | C61: 0.07 | D61: 100000 | E61: =D61*C61 -> 7000
B62: LEEK | C62: 0.15 | D62: 25000 | E62: 4000
B63: SPRING ONION | C63: 0.07 | D63: 80000 | E63: 6000
B64: TOMATO | C64: 1 | D64: 25000 | E64: =D64*C64 -> 25000
B65: COCONUT CREAM (KARA) | C65: 1 | D65: 220000 | E65: =D65*C65 -> 220000
B66: TOMATO KETCHUP/ SAUCE | C66: 4 | D66: 25000 | E66: =D66*C66 -> 100000
B67: CHILLI SAUCE | C67: 5 | D67: 35000 | E67: =D67*C67 -> 175000
B68: PARSLEY | C68: 0.1 | D68: 100000 | E68: =D68*C68 -> 10000
B69: CORIANDER | C69: 0.1 | D69: 80000 | E69: =D69*C69 -> 8000
B70: IMPORTED LEMON | C70: 1 | D70: 70000 | E70: =D70*C70 -> 70000
B71: BASIL | C71: 0.1 | D71: 80000 | E71: =D71*C71 -> 8000
B72: MINT | C72: 0.1 | D72: 80000 | E72: =D72*C72 -> 8000
B73: LIME | C73: 0.2 | D73: 30000 | E73: =D73*C73 -> 6000
B74: DOUBLE ZERO | C74: 1 | D74: 220000 | E74: =D74*C74 -> 220000
B75: TORTILLA WRAP | C75: 1 | D75: 100000 | E75: =D75*C75 -> 100000
B76: DARK CHOCOLATE COMPOUND | C76: 1 | D76: 80000 | E76: =D76*C76 -> 80000
A77: 46119 | B77: SESAME DRESSING | C77: 2 | D77: 120000 | E77: =D77*C77 -> 240000 | F77: =SUM(E77:E88) -> 1870000
B78: SALAD OIL | C78: 1 | D78: 210000 | E78: =D78*C78 -> 210000
B79: CASHEW NUT | C79: 1 | D79: 160000 | E79: =D79*C79 -> 160000
B80: PARSLEY | C80: 0.1 | D80: 100000 | E80: =D80*C80 -> 10000
B81: TORTILLA WRAP | C81: 1 | D81: 100000 | E81: =D81*C81 -> 100000
B82: PARMESAN CHEESE (BLOCK) | C82: 1 | D82: 275000 | E82: =D82*C82 -> 275000
B83: FETA CHEESE | C83: 2 | D83: 90000 | E83: =D83*C83 -> 180000
B84: MILAC WHIPPING CREAM | C84: 2 | D84: 100000 | E84: =D84*C84 -> 200000
B85: CREAM CHEESE | C85: 2 | D85: 170000 | E85: =D85*C85 -> 340000
B86: THYME | C86: 0.1 | D86: 250000 | E86: =D86*C86 -> 25000
B87: CHOCO CHIPS | C87: 2 | D87: 30000 | E87: =D87*C87 -> 60000
B88: IMPORTED LEMON | C88: 1 | D88: 70000 | E88: =D88*C88 -> 70000
A89: 46120 | B89: GREEN LETTUCE | C89: 0.4 | D89: 45000 | E89: =D89*C89 -> 18000 | F89: =SUM(E89:E93) -> 492000
B90: GREEN LETTUCE | C90: 0.3 | D90: 45000 | E90: 14000
B91: ROMA KELAPA | C91: 2 | D91: 15000 | E91: =D91*C91 -> 30000
B92: MIX BERRY | C92: 1 | D92: 130000 | E92: =D92*C92 -> 130000
B93: MILAC WHIPPING CREAM | C93: 3 | D93: 100000 | E93: =D93*C93 -> 300000
A94: 46122 | B94: SOUR CREAM | C94: 2 | D94: 170000 | E94: =D94*C94 -> 340000 | F94: =SUM(E94:E111) -> 2885000
B95: MILAC WHIPPING CREAM | C95: 5 | D95: 100000 | E95: =D95*C95 -> 500000
B96: FETA CHEESE | C96: 2 | D96: 90000 | E96: =D96*C96 -> 180000
B97: TORTILLA WRAP | C97: 3 | D97: 100000 | E97: =D97*C97 -> 300000
B98: SOY SAUCE | C98: 1 | D98: 20000 | E98: =D98*C98 -> 20000
B99: COCOA POWDER (B) | C99: 2 | D99: 50000 | E99: =D99*C99 -> 100000
B100: CHOCO CHIPS | C100: 2 | D100: 30000 | E100: =D100*C100 -> 60000
B101: COCONUT CREAM (KARA) | C101: 1 | D101: 220000 | E101: =D101*C101 -> 220000
B102: OREGANO | C102: 2 | D102: 30000 | E102: =D102*C102 -> 60000
B103: YEAST | C103: 1 | D103: 60000 | E103: =D103*C103 -> 60000
B104: DOUBLE ZERO | C104: 1 | D104: 220000 | E104: =D104*C104 -> 220000
...

Sheet SEDANA JAYA (Groceries)
A1: DATE | B1: INV NO. | C1: ITEM | D1: QYT | E1: PRICE | F1: SUBTOTAL | G1: TOTAL | H1: =SUM(G:G) -> 29623780
A2: 46113 | B2: 30858 | C2: ZUCCHINI | D2: 1 | E2: 55000 | F2: =E2*D2 -> 55000 | G2: =SUM(F2:F23) -> 1281800
C3: TOMATO | D3: 2 | E3: 25000 | F3: =E3*D3 -> 50000
C4: CARROT | D4: 1 | E4: 25000 | F4: =E4*D4 -> 25000
C5: RED PEPPER | D5: 0.5 | E5: 130000 | F5: =E5*D5 -> 65000
C6: FRESH MILK (DIAMOND) | D6: 3 | E6: 35000 | F6: =E6*D6 -> 105000
C7: EGG | D7: 3 | E7: 66000 | F7: =E7*D7 -> 198000
C8: POTATO | D8: 5 | E8: 25000 | F8: =E8*D8 -> 125000
C9: BANANA | D9: 2 | E9: 25000 | F9: =E9*D9 -> 50000
C10: WHITE SUGAR | D10: 2 | E10: 30000 | F10: =E10*D10 -> 60000
C11: EDAMAME | D11: 1 | E11: 55000 | F11: =E11*D11 -> 55000
C12: MANGO | D12: 1 | E12: 55000 | F12: =E12*D12 -> 55000
C13: AVOCADO | D13: 1 | E13: 40000 | F13: =E13*D13 -> 40000
C14: MUSHROOM BUTTON | D14: 1 | E14: 60000 | F14: =E14*D14 -> 60000
... C23: AMANDA BUTTER | D23: 2 | E23: 45000 | F23: =E23*D23 -> 90000
A24: 46114 | B24: 30876 | C24: ENGLISH SPINACH | D24: 0.5 | E24: 75000 | F24: =E24*D24 -> 37500 | G24: =SUM(F24:F44) -> 1746700
C25: BIG RED CHILLI | D25: 0.2 | E25: 75000 | F25: =E25*D25 -> 15000
C26: SHALLOT | D26: 0.2 | E26: 61000 | F26: =E26*D26 -> 12200
C27: GARLIC | D27: 0.2 | E27: 55000 | F27: =E27*D27 -> 11000
C28: ZUCCHINI | D28: 1 | E28: 60000 | F28: =E28*D28 -> 60000
C29: TOMATO | D29: 1 | E29: 26000 | F29: =E29*D29 -> 26000
C30: EGGPLANT | D30: 1 | E30: 15000 | F30: =E30*D30 -> 15000
C31: MUSHROOM SHIMEJI | D31: 2 | E31: 55000 | F31: =E31*D31 -> 110000
C32: FRESH MILK (DIAMOND) | D32: 4 | E32: 35000 | F32: =E32*D32 -> 140000
C33: TOTOLE (1KG) | D33: 2 | E33: 160000 | F33: =E33*D33 -> 320000
C34: WHITE SUGAR | D34: 2 | E34: 30000 | F34: =E34*D34 -> 60000
C35: PEANUT | D35: 1 | E35: 95000 | F35: =E35*D35 -> 95000
C36: EGG | D36: 3 | E36: 72000 | F36: =E36*D36 -> 216000
... C44: AVOCADO | D44: 1 | E44: 45000 | F44: =E44*D44 -> 45000
A45: 46114 | B45: 30879 | C45: CHERRY RED TOMATOES | D45: 0.5 | E45: 65000 | F45: =E45*D45 -> 32500 | G45: =SUM(F45:F46) -> 79500
C46: CHERRY YELLOW TOMATOES | D46: 0.5 | E46: 94000 | F46: =E46*D46 -> 47000
A47: 46115 | B47: 30900 | C47: ASPARAGUS | D47: 1 | E47: 200000 | F47: =E47*D47 -> 200000 | G47: =SUM(F47:F67) -> 1940800
C48: TOMATO | D48: 1 | E48: 26000 | F48: =E48*D48 -> 26000
C49: GREEN PEPPER | D49: 1 | E49: 83000 | F49: =E49*D49 -> 83000
C50: DRAGON FRUIT | D50: 2 | E50: 35000 | F50: =E50*D50 -> 70000
C51: SHALLOT | D51: 0.5 | E51: 61000 | F51: =E51*D51 -> 30500
C52: MUSHROOM BUTTON | D52: 3 | E52: 60000 | F52: =E52*D52 -> 180000
C53: BANANA | D53: 6 | E53: 25000 | F53: =E53*D53 -> 150000
C54: WHITE SUGAR | D54: 2 | E54: 30000 | F54: =E54*D54 -> 60000
C55: POTATO | D55: 5 | E55: 25000 | F55: =E55*D55 -> 125000
C56: ONION | D56: 5 | E56: 40000 | F56: =E56*D56 -> 200000
C57: EGG | D57: 5 | E57: 72000 | F57: =E57*D57 -> 360000
C58: ICEBERG | D58: 0.3 | E58: 45000 | F58: =E58*D58 -> 13500
C59: CHERRY RED TOMATOES | D59: 0.2 | E59: 65000 | F59: =E59*D59 -> 13000
... C67: FRESH MILK (DIAMOND) | D67: 3 | E67: 35000 | F67: =E67*D67 -> 105000
A68: 46116 | B68: 30915 | C68: ASPARAGUS | D68: 1 | E68: 200000 | F68: =E68*D68 -> 200000 | G68: =SUM(F68:F88) -> 1273600
C69: BIG RED CHILLI | D69: 0.3 | E69: 72000 | F69: =E69*D69 -> 21600
C70: CUCUMBER | D70: 1 | E70: 18000 | F70: =E70*D70 -> 18000
C71: CARROT | D71: 1 | E71: 25000 | F71: =E71*D71 -> 25000
C72: TOMATO | D72: 1 | E72: 26000 | F72: =E72*D72 -> 26000
C73: YELLOW PEPPER | D73: 0.5 | E73: 115000 | F73: =E73*D73 -> 57500
C74: RED PEPPER | D74: 0.5 | E74: 100000 | F74: =E74*D74 -> 50000
C75: EGGPLANT | D75: 1 | E75: 15000 | F75: =E75*D75 -> 15000
C76: DRAGON FRUIT | D76: 1 | E76: 35000 | F76: =E76*D76 -> 35000
C77: EGG | D77: 3 | E77: 72000 | F77: =E77*D77 -> 216000
C78: POTATO | D78: 4.5 | E78: 25000 | F78: =E78*D78 -> 112500
C79: WHITE SUGAR | D79: 2 | E79: 30000 | F79: =E79*D79 -> 60000
C80: CAKRA FLOUR | D80: 5 | E80: 20000 | F80: =E80*D80 -> 100000
... C88: ICEBERG | D88: 0.5 | E88: 45000 | F88: =E88*D88 -> 22500
A89: 46116 | B89: 30916 | C89: MUSHROOM BUTTON | D89: 1 | E89: 60000 | F89: =E89*D89 -> 60000 | G89: =SUM(F89) -> 60000
A90: 46117 | B90: 30943 | C90: FRESH MILK (DIAMOND) | D90: 4 | E90: 35000 | F90: =E90*D90 -> 140000 | G90: =SUM(F90:F105) -> 1475000
C91: DOLPIN SALT | D91: 2 | E91: 25000 | F91: =E91*D91 -> 50000
C92: BROWN SUGAR | D92: 1 | E92: 45000 | F92: =E92*D92 -> 45000
C93: POTATO | D93: 10 | E93: 25000 | F93: =E93*D93 -> 250000
C94: SWEET POTATO | D94: 5 | E94: 35000 | F94: =E94*D94 -> 175000
C95: ONION | D95: 5 | E95: 40000 | F95: =E95*D95 -> 200000
C96: EGGPLANT | D96: 1 | E96: 15000 | F96: =E96*D96 -> 15000
C97: ENGLISH SPINACH | D97: 0.5 | E97: 75000 | F97: =E97*D97 -> 37500
C98: GREEN LETTUCE | D98: 0.3 | E98: 50000 | F98: =E98*D98 -> 15000
C99: ROMAINE LETTUCE | D99: 0.3 | E99: 70000 | F99: =E99*D99 -> 21000
C100: STRAWBERRY | D100: 0.3 | E100: 105000 | F100: =E100*D100 -> 31500
C101: WHITE PEAR | D101: 2 | E101: 50000 | F101: =E101*D101 -> 100000
C102: AVOCADO | D102: 1 | E102: 45000 | F102: =E102*D102 -> 45000
... C105: MAIZENA FLOUR | D105: 2 | E105: 30000 | F105: =E105*D105 -> 60000
A106: 46118 | B106: 30948 | C106: FRESH MILK (DIAMOND) | D106: 3 | E106: 35000 | F106: =E106*D106 -> 105000 | G106: =SUM(F106:F126) -> 1471200
C107: MUSHROOM SHIMEJI | D107: 2 | E107: 55000 | F107: =E107*D107 -> 110000
C108: ZUCCHINI | D108: 1 | E108: 60000 | F108: =E108*D108 -> 60000
C109: GREEN PEPPER | D109: 0.5 | E109: 83000 | F109: =E109*D109 -> 41500
C110: DRAGON FRUIT | D110: 1 | E110: 35000 | F110: =E110*D110 -> 35000
C111: TOMATO | D111: 1 | E111: 26000 | F111: =E111*D111 -> 26000
C112: WHITE SUGAR | D112: 2 | E112: 30000 | F112: =E112*D112 -> 60000
C113: RED RICE | D113: 1 | E113: 45000 | F113: =E113*D113 -> 45000
C114: POTATO | D114: 5 | E114: 25000 | F114: =E114*D114 -> 125000
C115: SWEET POTATO | D115: 3 | E115: 35000 | F115: =E115*D115 -> 105000
C116: EGG | D116: 5 | E116: 72000 | F116: =E116*D116 -> 360000
C117: AVOCADO | D117: 1.5 | E117: 45000 | F117: =E117*D117 -> 67500
C118: GREEN APPLE | D118: 1 | E118: 55000 | F118: =E118*D118 -> 55000
... C126: BEANS | D126: 0.2 | E126: 15000 | F126: =E126*D126 -> 3000
A127: 46119 | B127: 31038 | C127: WHITE SESAME SEED | D127: 0.3 | E127: 120000 | F127: =E127*D127 -> 36000 | G127: =SUM(F127:F147) -> 1129000
C128: BLACK SESAME SEED | D128: 0.3 | E128: 120000 | F128: =E128*D128 -> 36000
C129: BANANA | D129: 5.2 | E129: 25000 | F129: =E129*D129 -> 130000
C130: POTATO | D130: 10 | E130: 25000 | F130: =E130*D130 -> 250000
C131: SWEET POTATO | D131: 3 | E131: 35000 | F131: =E131*D131 -> 105000
C132: BIG RED CHILLI | D132: 0.2 | E132: 72000 | F132: =E132*D132 -> 14400
C133: CHILLI PEPPER | D133: 0.2 | E133: 95000 | F133: =E133*D133 -> 19000
C134: SHALLOT | D134: 0.3 | E134: 61000 | F134: =E134*D134 -> 18300
C135: GARLIC | D135: 0.3 | E135: 55000 | F135: =E135*D135 -> 16500
C136: TOMATO | D136: 2 | E136: 26000 | F136: =E136*D136 -> 52000
C137: FRESH MILK (DIAMOND) | D137: 2 | E137: 35000 | F137: =E137*D137 -> 70000
C138: BABY ROMAINE | D138: 0.5 | E138: 65000 | F138: =E138*D138 -> 32500
...

Sheet AD supplier (Groceries)
A1: DATE | B1: DATE | C1: INV NO. | D1: ITEM | E1: QYT | F1: PRICE | G1: SUBTOTAL | H1: TOTAL | I1: BILLS | J1: =H22 -> 13063000
A2: 46084 | B2: 46114 | C2: ADS-232974 | D2: MOZARELLA CHEESE | E2: 6.9 | F2: 120000 | G2: =F2*E2 -> 828000 | H2: =SUM(G2:G6) -> 1513000
D3: PARMESAN CHEESE GRATED | E3: 1 | F3: 210000 | G3: =F3*E3 -> 210000
A4: 46084 | D4: LA FONTE PASTA FETTUCINE | E4: 5 | F4: 30000 | G4: =F4*E4 -> 150000
A5: 46094 | D5: LA FONTE PASTA PENNEZITI RIGATI | E5: 5 | F5: 30000 | G5: =F5*E5 -> 150000
D6: LA FONTE PASTA SPAGHETTI | E6: 5 | F6: 35000 | G6: =F6*E6 -> 175000
B7: 46114 | C7: ADS-233073 | D7: BORGES EXTRA VIRGIN OIL 5 L | E7: 1 | F7: 1300000 | G7: =F7*E7 -> 1300000 | H7: =SUM(G7) -> 1300000
B8: 46116 | C8: ADS-233702 | D8: TOMATOES PEELED MERKO | E8: 18 | F8: 100000 | G8: =F8*E8 -> 1800000 | H8: =SUM(G8:G9) -> 1980000
D9: CHEESE SLICE YELLOW (ANCHOR) | E9: 1 | F9: 180000 | G9: =F9*E9 -> 180000
B10: 46116 | C10: ADS-233707 | D10: MOZARELLA CHEESE | E10: 6.9 | F10: 120000 | G10: =F10*E10 -> 828000 | H10: =SUM(G10) -> 828000
B11: 46119 | C11: ADS-234412 | D11: OIL RB JAR | E11: 3 | F11: 380000 | G11: =F11*E11 -> 1140000 | H11: =SUM(G11) -> 1140000
B12: 46128 | C12: ADS-237423 | D12: TOMATOES PEELED MERKO | E12: 18 | F12: 100000 | G12: =F12*E12 -> 1800000 | H12: =SUM(G12:G14) -> 4952000
D13: MOZARELLA CHEESE | E13: 4.6 | F13: 120000 | G13: =F13*E13 -> 552000
D14: BORGES EXTRA VIRGIN OIL 5 L | E14: 2 | F14: 1300000 | G14: =F14*E14 -> 2600000
B15: 46128 | C15: ADS-237686 | D15: PARMESAN CHEESE GRATED | E15: 1 | F15: 210000 | G15: =F15*E15 -> 210000 | H15: =SUM(G15) -> 210000
B16: 46128 | C16: ADS- 237426 | D16: OIL RB JAR | E16: 3 | F16: 380000 | G16: =F16*E16 -> 1140000 | H16: =SUM(G16) -> 1140000
H22: =SUM(H2:H21) -> 13063000

Sheet AGUS SEAFOOD
A1: DATE | B1: DESCRIPTION | C1: QUANTITY | D1: PRICE | E1: SUBTOTAL | F1: TOTAL | G1: INV. NO | H1: BILLS | I1: =E59 -> 7908500
A2: 46118 | B2: SALMON FILLET | C2: 5.3 | D2: 290000 | E2: =D2*C2 -> 1537000 | F2: =SUM(E2) -> 1537000 | G2: 854
A3: 46122 | B3: SALMON FILLET | C3: 5.7 | D3: 290000 | E3: =D3*C3 -> 1653000 | F3: =SUM(E3:E4) -> 2185000 | G3: 816
B4: TUNA | C4: 5.6 | D4: 95000 | E4: =D4*C4 -> 532000
A5: 46126 | B5: TUNA | C5: 5.3 | D5: 95000 | E5: =D5*C5 -> 503500 | F5: =SUM(E5:E6) -> 1489500 | G5: 783
B6: SALMON FILLET | C6: 3.4 | D6: 290000 | E6: =D6*C6 -> 986000
A7: 46128 | B7: SALMON FILLET | C7: 5.6 | D7: 290000 | E7: =D7*C7 -> 1624000 | F7: =SUM(E7) -> 1624000 | G7: 4
A8: 46132 | B8: SALMON FILLET | C8: 3.7 | D8: 290000 | E8: =D8*C8 -> 1073000 | F8: =SUM(E8) -> 1073000 | G8: 60
A59: GRAND TOTAL | E59: =SUM(F2:F58) -> 7908500

Sheet RAFI SEAFOOD (Seafood)
A1: DATE | B1: DESCRIPTION | C1: INV NO. | D1: QTY | E1: PRICE | F1: SUBTOTAL | G1: TOTAL | H1: BILLS | I1: =E58 -> 12037000
A2: 46114 | B2: PRAWN | C2: N/A | D2: 3 | E2: 185000 | F2: =E2*D2 -> 555000 | G2: =SUM(F2:F4) -> 2029500
B3: TUNA | D3: 6.3 | E3: 115000 | F3: =E3*D3 -> 724500
B4: MINCED BEEF | D4: 5 | E4: 150000 | F4: =E4*D4 -> 750000
A5: 46117 | B5: PRAWN | C5: N/A | D5: 4 | E5: 185000 | F5: =E5*D5 -> 740000 | G5: =SUM(F5:F8) -> 2137000
B6: SQUID TUBE | D6: 3 | E6: 90000 | F6: =E6*D6 -> 270000
B7: TUNA | D7: 7 | E7: 115000 | F7: =E7*D7 -> 805000
B8: MAHI-MAHI | D8: 2.8 | E8: 115000 | F8: =E8*D8 -> 322000
A9: 46121 | B9: SQUID TUBE | C9: 563 | D9: 2 | E9: 100000 | F9: =E9*D9 -> 200000 | G9: =SUM(F9:F11) -> 1735500
B10: PRAWN | D10: 6 | E10: 185000 | F10: =E10*D10 -> 1110000
B11: MAHI-MAHI | D11: 3.7 | E11: 115000 | F11: =E11*D11 -> 425500
A12: 46123 | B12: CHICKEN BREAST | C12: 584 | D12: 10 | E12: 65000 | F12: =E12*D12 -> 650000 | G12: =SUM(F12:F15) -> 2300000
B13: CHICKEN LEG | D13: 10 | E13: 65000 | F13: =E13*D13 -> 650000
B14: CHICKEN WING | D14: 5 | E14: 50000 | F14: =E14*D14 -> 250000
B15: MINCED BEEF | D15: 5 | E15: 150000 | F15: =E15*D15 -> 750000
A16: 46127 | B16: TUNA | C16: 608 | D16: 5 | E16: 115000 | F16: =E16*D16 -> 575000 | G16: =SUM(F16:F18) -> 1515000
B17: PRAWN | D17: 4 | E17: 185000 | F17: =E17*D17 -> 740000
B18: SQUID TUBE | D18: 2 | E18: 100000 | F18: =E18*D18 -> 200000
A19: 46131 | B19: MAHI-MAHI | C19: 642 | D19: 2.2 | E19: 115000 | F19: =E19*D19 -> 253000 | G19: =SUM(F19:F23) -> 2320000
B20: TUNA | D20: 5.8 | E20: 115000 | F20: =E20*D20 -> 667000
B21: CHICKEN LEG | D21: 5 | E21: 65000 | F21: =E21*D21 -> 325000
B22: CHICKEN BREAST | D22: 5 | E22: 65000 | F22: =E22*D22 -> 325000
B23: MINCED BEEF | D23: 5 | E23: 150000 | F23: =E23*D23 -> 750000
E58: =SUM(G2:G57) -> 12037000

Sheet ABISEKA (FRESH MILK)
A1: DATE | B1: INV NO. | C1: DESCRIPTION | D1: QUANTITY | E1: PRICE | F1: SUBTOTAL | G1: TOTAL | H1: DUE DATE | I1: PAYMENT STATUS | J1: BILLS | K1: =E24 -> 1350000
A2: 46115 | B2: 8948 | C2: FRESH MILK | D2: 70 | E2: 13500 | F2: =E2*D2 -> 945000 | G2: =SUM(F2) -> 945000 | H2: 46129 | I2: UNPAID
A3: 46128 | B3: 9181 | C3: FRESH MILK | D3: 30 | E3: 13500 | F3: =E3*D3 -> 405000 | G3: =SUM(F3) -> 405000 | H3: 46142 | I3: UNPAID
E24: {=SUM(G2:G23)-SUM(SUMIFS(G:G,I:I,{"PAID","MAKER"}))} -> 1350000

Sheet FORNO (Burger&Croissant)
A1: DATE | B1: DESCRIPTION | C1: QUANTITY | D1: PRICE | E1: SUBTOTAL | F1: TOTAL | G1: AFTER TAX | H1: BILLS | I1: =D26 -> 1337550
A2: 46115 | B2: BRIOCHE BUN | C2: 25 | D2: 5000 | E2: =D2*C2 -> 125000 | F2: =SUM(E2:E3) -> 270000 | G2: =(F2*11%)+F2 -> 299700
B3: CROISSANT PLAIN | C3: 10 | D3: 14500 | E3: =D3*C3 -> 145000
A4: 46121 | B4: BRIOCHE BUN | C4: 30 | D4: 5000 | E4: =D4*C4 -> 150000 | F4: =SUM(E4:E5) -> 295000 | G4: =(F4*11%)+F4 -> 327450
B5: CROISSANT PLAIN | C5: 10 | D5: 14500 | E5: =D5*C5 -> 145000
A6: 46126 | B6: BRIOCHE BUN | C6: 30 | D6: 5000 | E6: =D6*C6 -> 150000 | F6: =SUM(E6:E7) -> 295000 | G6: =(F6*11%)+F6 -> 327450
B7: CROISSANT PLAIN | C7: 10 | D7: 14500 | E7: =D7*C7 -> 145000
A8: 46128 | B8: CROISSANT PLAIN | C8: 10 | D8: 14500 | E8: =D8*C8 -> 145000 | F8: =SUM(E8:E9) -> 245000 | G8: =(F8*11%)+F8 -> 271950
B9: BRIOCHE BUN | C9: 20 | D9: 5000 | E9: =D9*C9 -> 100000
A10: 46131 | B10: BRIOCHE BUN | C10: 20 | D10: 5000 | E10: =D10*C10 -> 100000 | F10: =SUM(E10) -> 100000 | G10: =(F10*11%)+F10 -> 111000
E11: =D11*C11 -> 0
E12: =D12*C12 -> 0
E13: =D13*C13 -> 0
E14: =D14*C14 -> 0
E15: =D15*C15 -> 0
E16: =D16*C16 -> 0
E17: =D17*C17 -> 0
E18: =D18*C18 -> 0
E19: =D19*C19 -> 0
E20: =D20*C20 -> 0
E21: =D21*C21 -> 0
E22: =D22*C22 -> 0
... E25: =D25*C25 -> 0
D26: =SUM(G:G) -> 1337550

Sheet Kemang Food (Salami)
A1: DATE | B1: INV NO. | C1: DESCRIPTION | D1: QUANTITY | E1: PRICE | F1: SUBTOTAL | G1: TOTAL | H1: DISC | I1: PPN 11% | J1: TOTAL | K1: PAYMENT STATUS | L1: BILLS | M1: =I24 -> 0
I2: =G2*11% -> 0 | J2: =SUM(G2)-H2+I2 -> 0
I24: =SUM(J:J)-SUMIF(K:K,"PAID*",J:J) -> 0

Sheet MAMA RADA PRODUCTION (Dumpling)
A1: DATE | B1: INV NO. | C1: DESCRIPTIONS | D1: QTY | E1: PRICE | F1: SUBTOTAL | G1: TOTAL | H1: BIILS | I1: =F12 -> 0
E12: GRAND TOTAL | F12: =SUM(G2:G11) -> 0

Sheet KSP (Chicken)
A1: DATE | B1: INV NO. | C1: DESCRIPTIONS | D1: QTY | E1: PRICE | F1: SUB TOTAL | G1: TOTAL | H1: BILLS | I1: =G26 -> 3184800
A2: 46113 | B2: B01124/PRN-R/2026 | C2: BONELESS BREAST TK SP | D2: 5.2 | E2: 53000 | F2: =E2*D2 -> 275600 | G2: =SUM(F2:F4) -> 1096300
C3: BONELESS LEG TK SP | D3: 11.9 | E3: 53000 | F3: =E3*D3 -> 630700
C4: WINGS TD | D4: 5 | E4: 38000 | F4: =E4*D4 -> 190000
A5: 46119 | B5: BO1207/PRN-R/2026 | C5: BONELESS BREAST TK SP | D5: 5 | E5: 51000 | F5: =E5*D5 -> 255000 | G5: =SUM(F5:F7) -> 1104200
C6: BONELESS LEG TK SP | D6: 13 | E6: 51000 | F6: =E6*D6 -> 663000
C7: WINGS TD | D7: 4.9 | E7: 38000 | F7: =E7*D7 -> 186200
A8: 46126 | B8: B01356/PRN-R/2026 | C8: BONELESS BREAST | D8: 5.6 | E8: 51000 | F8: =E8*D8 -> 285600 | G8: =SUM(F8:F9) -> 984300
C9: BONELESS LEG | D9: 13.7 | E9: 51000 | F9: =E9*D9 -> 698700
F10: =E10*D10 -> 0 | G10: =SUM(F10:F11) -> 0
F11: =E11*D11 -> 0
A26: GRAND TOTAL | G26: =SUM(G2:G25) -> 3184800

Sheet SURYA CIPTA NIAGA BALI (Beef)
A1: DATE | B1: INV NO. | C1: DESCRIPTIONS | D1: QTY | E1: PRICE | F1: SUBTOTAL | G1: TOTAL | H1: DUE DATE | I1: STATUS | J1: BILLS | K1: =F14 -> 17031900 | L1: =K1+'[1]WARUNG EKA (Drinks, Etc)'!$H$1 -> 24163900
A2: 46114 | B2: 2604/FK-0173 | C2: TOP SIDE BLACK ANGUS GF ONYX | D2: 10.15 | E2: 250000 | F2: =E2*D2 -> 2537500 | G2: =SUM(F2:F3) -> 5383300 | H2: 46144 | I2: UNPAID
C3: STRIPLOIN ICHI BROWN | D3: 15.81 | E3: 180000 | F3: =E3*D3 -> 2845800
A4: 46128 | B4: 2604/FK-1790 | C4: STRIPLOIN ICHI BROWN | D4: 7.03 | E4: 180000 | F4: =E4*D4 -> 1265400 | G4: =SUM(F4:F5) -> 6335400 | H4: 46158 | I4: UNPAID
C5: TOP SIDE BLACK ANGUS GF ONYX | D5: 20.28 | E5: 250000 | F5: =E5*D5 -> 5070000
A6: 46132 | B6: 2604/FK-2153 | C6: TOP SIDE BLACK ANGUS GF ONYX | D6: 12.44 | E6: 250000 | F6: =E6*D6 -> 3110000 | G6: =SUM(F6:F7) -> 5313200 | H6: 46162 | I6: UNPAID
C7: STRIPLOIN ICHI BROWN | D7: 12.24 | E7: 180000 | F7: =E7*D7 -> 2203200
A14: TOTAL | F14: {=SUM(G:G)-SUM(SUMIFS(G:G,I:I,{"PAID","MAKER"}))} -> 17031900

Sheet MULIA JAYA (PASSION FRUIT)
A1: DATE | B1: DESCRIPTIONS | C1: QTY | D1: PRICE | E1: SUBTOTAL | F1: TOTAL | G1: STATUS | H1: BILLS | I1: =E13 -> 0
A2: 46115 | B2: PASSION FRUIT PUREE | C2: 6 | D2: 50000 | E2: =D2*C2 -> 300000 | F2: =SUM(E2) -> 300000 | G2: PAID
A13: TOTAL | E13: =SUM(F:F)-SUMIF(G:G,"PAID",F:F) -> 0

Sheet BAYU AGNI MERTA (Gas)
A1: DATE | B1: INV NO. | C1: DESCRIPTIONS | D1: QTY | E1: PRICE | F1: TOTAL | G1: BILLS | H1: =E5 -> 7740000
A2: 46130 | B2: 1915 | C2: LPG 50 KG | D2: 9 | E2: 860000 | F2: =E2*D2 -> 7740000
F3: =E3*D3 -> 0
F4: =D4*E4 -> 0
A5: TOTAL | E5: =SUM(F2:F4) -> 7740000

Sheet Joy Green (Mix Berry)
A1: NO | B1: DATE | C1: TOTAL | D1: PC | E1: STATUS | F1: =D3 -> 0
A3: Total | D3: =SUM(C2:C2) -> 0

Sheet CELEBRITY BAKERY (Bakery)
A1: DATE | B1: INV.NO | C1: DESCRIPTION | D1: QTY | E1: PRICE | F1: SUBTOTAL | G1: TOTAL | H1: BILLS | I1: =E5 -> 160000
A2: 46128 | B2: DLV/CUS00453/160426/00001 | C2: SOUR BREAD 500 GR GLUTTENFREE | D2: 2 | E2: 50000 | F2: =E2*D2 -> 100000 | G2: =SUM(F2:F3) -> 160000
C3: BAQUETTE GLUTTENFREE 300 GR | D3: 2 | E3: 30000 | F3: =E3*D3 -> 60000
A5: TOTAL | E5: =SUM(G2:G4) -> 160000

Sheet Krop (Edible flower)
A1: DATE | B1: INV.NO | C1: DESCRIPTION | D1: QTY | E1: PRICE | F1: SUBTOTAL | G1: TOTAL | H1: BILLS | I1: =G10 -> 0
A10: TOTAL | G10: =SUM(G2:G9) -> 0

Sheet Boiler (Dumplings&Syrniki)
A1: DATE | B1: INV.NO | C1: DESCRIPTION | D1: QTY | E1: PRICE | F1: SUBTOTAL | G1: TOTAL | H1: DISCOUNT | I1: TOTAL AFTER DISC | J1: TAX | K1: TOTAL AFTER DISC & TAX | L1: STATUS | M1: BILLS | N1: =H5 -> 0
F2: =D2*E2 -> 0 | G2: =SUM(F2:F4) -> 0 | H2: 0 | I2: =G2-H2 -> 0 | J2: =I2*10% -> 0 | K2: =I2+J2 -> 0 | L2: UNPAID
F3: =D3*E3 -> 0
F4: =D4*E4 -> 0
A5: GRAND TOTAL | H5: =SUM(K:K)-SUMIF(L:L,"PAID*",K:K) -> 0

Sheet TOTAL
A1: SUPPLIER | B1: Total
A2: TEGAL JAYA | B2: ='TEGAL JAYA (Groceries)'!H1 -> 2687700
A3: BU BUNGA | B3: ='BUK BUNGA (Groceries)'!G1 -> 25635000
A4: SEDANA JAYA | B4: ='SEDANA JAYA (Groceries)'!H1 -> 29623780
A5: AD SUPPLIER | B5: ='AD supplier (Groceries)'!J1 -> 13063000
A6: AGUS SEAFOOD | B6: ='AGUS SEAFOOD'!I1 -> 7908500
A7: RAFI SEAFOOD | B7: ='RAFI SEAFOOD (Seafood)'!I1 -> 12037000
A8: ABISEKA | B8: ='ABISEKA (FRESH MILK)'!K1 -> 1350000
A9: FORNO | B9: ='FORNO (Burger&Croissant)'!I1 -> 1337550
A10: KEMANG FOOD | B10: ='Kemang Food (Salami)'!M1 -> 0
A11: MAMA RADA PRODUCTION | B11: ='MAMA RADA PRODUCTION (Dumpling)'!I1 -> 0
A12: KSP | B12: ='KSP (Chicken)'!I1 -> 3184800
A13: SURYA CIPTA NIAGA BALI | B13: ='SURYA CIPTA NIAGA BALI (Beef)'!K1 -> 17031900
A14: MULIA JAYA | B14: ='MULIA JAYA (PASSION FRUIT)'!I1 -> 0
A15: BAYU AGNI MERTA | B15: ='BAYU AGNI MERTA (Gas)'!H1 -> 7740000
A16: JOY GREEN | B16: ='Joy Green (Mix Berry)'!F1 -> 0
A17: CELEBRITY BAKERY | B17: ='CELEBRITY BAKERY (Bakery)'!I1 -> 160000
A18: KROP NATIION | B18: ='Krop (Edible flower)'!I1 -> 0
A19: BOILER | B19: ='Boiler (Dumplings&Syrniki)'!N1 -> 0
A20: TOTAL | B20: =SUM(B2:B19) -> 121759230
